{
  "list": [
    {
      "w": 1704636528751,
      "title": "Молодёжка",
      "app": "index",
      "dsc": "",
      "topic": "",
      "days": [
        {
          "list": [
            {
              "type": 0,
              "mi": 0,
              "tgAlert": 1,
              "atts": {},
              "tgInform": 0,
              "rate": {
                "0": [0, ""],
                "4": [5, "Хорошо общаться с мужем 🥰\nи вкусно кофе ☕️"]
              },
              "tm": 30
            },
            {
              "type": 1,
              "mi": 1,
              "tgAlert": 1,
              "atts": {
                "[cm]:coms": {
                  "comws": [1611851960664, 1611851960664],
                  "eventw": 1610962824551
                }
              },
              "tgInform": 0,
              "rate": {
                "0": [0, "от"],
                "4": [0, ""]
              }
            },
            {
              "type": 2,
              "mi": 2,
              "tgAlert": 1,
              "atts": {},
              "tgInform": 0,
              "dsc": "",
              "tm": 60,
              "rate": {
                "0": [0, ""]
              },
              "topic": ""
            },
            {
              "type": 3,
              "mi": 3,
              "tgInform": 0
            }
          ],
          "wup": 17,
          "mi": 0
        }
      ],
      "tatts": [
        {
          "description": "",
          "icon": "cast-outline",
          "initVal": {},
          "title": "Ход события",
          "R": 105,
          "U": 105,
          "mi": 0,
          "use": 113,
          "titles": ["лоывар", "ыволарыва"]
        }
      ],
      "types": [
        {
          "title": "Общение",
          "tm": 15
        },
        {
          "title": "Пение",
          "tm": 30,
          "atts": {
            "[cm]:coms": [-1]
          }
        },
        {
          "title": "Проповедь",
          "tm": 90
        },
        {
          "title": "Разъезд",
          "tm": 5
        }
      ],
      "start": 1729371600000,
      "ctrl": {
        "cats": ["Основное"],
        "users": [
          {
            "mi": 0,
            "nick": "gfirf",
            "fio": "Павел 💾",
            "login": "T166cbf17596a0c2919e4df1a6d54e66",
            "R": 127,
            "tgAlerts": 1,
            "tgId": 958383738,
            "tgInform": 1
          },
          {
            "fio": "danikpon",
            "login": "T7f21a14d3133065ca2e48254f87ecf3",
            "nick": "danikpon",
            "tgId": 370756745,
            "mi": 1,
            "tgInform": 1,
            "R": 127
          },
          {
            "fio": "Руслан",
            "login": "T6558fe287d2ea93be3e19bbe64b5dfc",
            "nick": "maunrus",
            "tgId": 521630606,
            "mi": 2,
            "R": 43,
            "tgInform": 0
          },
          {
            "fio": "yansmk",
            "login": "08a0e6ba7792e902569816a81b846b25",
            "nick": "yansmk",
            "mi": 3,
            "R": 21
          },
          {
            "fio": "Жменька💙",
            "login": "T2844a791f6cb5702a875a0bad8e9397",
            "nick": "Pashas_wife",
            "tgId": 1086988826,
            "mi": 4,
            "tgInform": 1,
            "R": 47
          },
          {
            "fio": "",
            "login": "T0798c1117b22e78af2e87c075b53ea2",
            "nick": "AndreyKartyshin",
            "tgId": 760378069,
            "mi": 5,
            "R": 47,
            "tgInform": 0
          },
          {
            "fio": "Андрей",
            "mi": 6,
            "R": 17
          },
          {
            "fio": "Денис Евдокимов",
            "login": "Ta6fc77b8901b55067f55c104839abde",
            "nick": "EvdDenis",
            "tgId": 426245780,
            "mi": 7,
            "R": 47
          },
          {
            "fio": "JESMYL",
            "login": "1cd799804adadac7bebf6f355fe7a58b",
            "nick": "JESMYL",
            "mi": 8,
            "R": 127
          },
          {
            "fio": "Юрий",
            "login": "T1c5a587ddebf63011b5aa6e54977b34",
            "nick": "t:esjimyimje",
            "tgId": 1206346301,
            "mi": 9,
            "R": 5
          },
          {
            "fio": "User",
            "login": "8f9bfe9d1345237cb3b2b205864da075",
            "nick": "User",
            "mi": 10
          }
        ],
        "roles": [
          {
            "mi": 0,
            "title": "Координатор",
            "icon": "github-outline",
            "user": 0
          },
          {
            "title": "",
            "mi": 1
          }
        ],
        "type": 3,
        "defu": 21
      },
      "lists": {
        "cats": [
          {
            "icon": "people-outline",
            "title": "Группа",
            "titles": ["Наставники", "Участники"]
          }
        ],
        "units": [
          {
            "cat": 0,
            "mi": 1,
            "title": "Первая",
            "dsc": ""
          }
        ]
      },
      "tgAlertsTime": 30,
      "tgInform": 1,
      "tgInformTime": 5,
      "games": {
        "criterias": [
          {
            "title": "ggggvvvbj",
            "sorts": []
          }
        ],
        "list": [
          {
            "title": "Новая игра",
            "teams": [],
            "mi": 0
          }
        ],
        "strikedUsers": []
      }
    },
    {
      "w": 1707030487401,
      "title": "Утреннее служение",
      "app": "index",
      "dsc": "",
      "topic": "",
      "days": [
        {
          "list": [
            {
              "type": 0,
              "mi": 0,
              "atts": {
                "[cm]:coms": {
                  "eventw": 1611470202200
                }
              },
              "tgInform": 1
            },
            {
              "type": 1,
              "mi": 1,
              "dsc": "Бизюк Валерий"
            },
            {
              "type": 0,
              "mi": 2,
              "tgInform": 0
            },
            {
              "type": 1,
              "mi": 3,
              "topic": "Взыскать и спасти погибшее | Лук 19:1-10",
              "dsc": "Юрий Матвиенко",
              "tgInform": 0
            },
            {
              "type": 0,
              "mi": 4,
              "tgInform": 0
            }
          ],
          "wup": 10,
          "mi": 0
        }
      ],
      "tatts": [],
      "types": [
        {
          "tm": 5,
          "title": "Пение ",
          "atts": {
            "[cm]:coms": [-1]
          }
        },
        {
          "tm": 45,
          "title": "Проповедь"
        }
      ],
      "tgInformTime": 5,
      "start": 1725742800000,
      "ctrl": {
        "cats": ["Основное"],
        "users": [
          {
            "fio": "danikpon",
            "login": "T7f21a14d3133065ca2e48254f87ecf3",
            "nick": "danikpon",
            "tgId": 370756745,
            "mi": 0,
            "R": 127,
            "tgInform": 1
          },
          {
            "fio": "Павел 💾",
            "login": "T166cbf17596a0c2919e4df1a6d54e66",
            "nick": "gfirf",
            "tgId": 958383738,
            "mi": 1
          },
          {
            "fio": "Артём ✞",
            "login": "T5bf2641668ea893e95047be453a5044",
            "nick": "artemkadjam",
            "tgId": 1035981397,
            "mi": 2
          }
        ],
        "roles": [
          {
            "mi": 0,
            "title": "Координатор",
            "icon": "github-outline",
            "user": 0
          }
        ],
        "type": 3,
        "defu": 43
      },
      "lists": {
        "cats": [
          {
            "icon": "people-outline",
            "title": "Группа",
            "titles": ["Наставники", "Участники"]
          },
          {
            "title": "",
            "icon": "list",
            "titles": ["Руководители", "Участники"]
          }
        ],
        "units": [
          {
            "cat": 0,
            "mi": 1,
            "title": "Первая",
            "dsc": ""
          }
        ]
      }
    },
    {
      "w": 1707303561013,
      "title": "Крымская молодёжка",
      "app": "index",
      "dsc": "",
      "topic": "",
      "days": [
        {
          "list": [
            {
              "type": 6,
              "mi": 5,
              "tm": 30,
              "tgInform": 0,
              "rate": {
                "1": [3, "Мало парковочных мест"]
              }
            },
            {
              "type": 0,
              "mi": 0,
              "tgInform": 0,
              "rate": {
                "1": [5, "Чаёк вкусный 🔥"]
              }
            },
            {
              "type": 1,
              "mi": 1,
              "tgInform": 0,
              "atts": {
                "[cm]:coms": {
                  "comws": [1548912465710, 1548917413824, 1610715483150, 1517854709000, 1628844861136, 1609761208284]
                }
              },
              "rate": {
                "1": [5, "Хорошая группа прославления 🥰"]
              }
            },
            {
              "type": 2,
              "mi": 2,
              "tgInform": 0,
              "dsc": "##Нейков И.И."
            },
            {
              "type": 3,
              "mi": 3,
              "tgInform": 0
            },
            {
              "type": 4,
              "mi": 4,
              "tgInform": 0
            }
          ],
          "wup": 15,
          "mi": 0
        }
      ],
      "tatts": [],
      "types": [
        {
          "title": "Чай, кофе",
          "tm": 30
        },
        {
          "title": "Поклонение",
          "tm": 60
        },
        {
          "title": "Проповедь",
          "tm": 60
        },
        {
          "title": "Свободное время",
          "tm": 30
        },
        {
          "title": "Ужин",
          "tm": 60
        },
        {
          "title": "Репетиция",
          "tm": 180
        },
        {
          "title": "Приезд",
          "tm": 30
        }
      ],
      "tgInformTime": 5,
      "start": 1707512400000,
      "ctrl": {
        "cats": ["Основное"],
        "users": [
          {
            "fio": "Павел 💾",
            "login": "T166cbf17596a0c2919e4df1a6d54e66",
            "nick": "gfirf",
            "tgId": 958383738,
            "mi": 0,
            "R": 127,
            "tgInform": 1
          },
          {
            "fio": "Джексон_С💙",
            "login": "T2844a791f6cb5702a875a0bad8e9397",
            "nick": "Pashas_wife",
            "tgId": 1086988826,
            "mi": 1,
            "R": 21,
            "tgInform": 1
          },
          {
            "fio": "danikpon",
            "login": "T7f21a14d3133065ca2e48254f87ecf3",
            "nick": "danikpon",
            "tgId": 370756745,
            "mi": 2,
            "R": 127
          },
          {
            "fio": "User",
            "login": "8f9bfe9d1345237cb3b2b205864da075",
            "nick": "User",
            "mi": 3,
            "R": 5
          },
          {
            "fio": "Artemkadjam",
            "login": "16d0e0d747fd06d1a3d91ecb00ed39ec",
            "nick": "Artemkadjam",
            "mi": 4,
            "R": 21
          }
        ],
        "roles": [
          {
            "mi": 0,
            "title": "Координатор",
            "icon": "github-outline",
            "user": 0
          }
        ],
        "type": 13,
        "defu": 5
      },
      "lists": {
        "cats": [
          {
            "icon": "people-outline",
            "title": "Группа",
            "titles": ["Наставники", "Участники"]
          }
        ],
        "units": [
          {
            "cat": 0,
            "mi": 1,
            "title": "Первая",
            "dsc": ""
          }
        ]
      }
    },
    {
      "title": "gggq",
      "app": "index",
      "dsc": "",
      "topic": "",
      "days": [
        {
          "list": [
            {
              "type": 0,
              "mi": 0,
              "dsc": "dqdqdwqd",
              "atts": {
                "[SCH]:custom:0": {
                  "comws": [1517639268000],
                  "[cm]:coms": {
                    "comws": [1517583318000, 1517518975000, 1517582537000]
                  }
                },
                "[cm]:coms": {
                  "comws": [1517743879000]
                }
              },
              "tgInform": 1
            }
          ],
          "wup": 7,
          "mi": 0
        }
      ],
      "tatts": [
        {
          "description": "sdfdf",
          "icon": "Attachment",
          "initVal": {},
          "title": "Песни на след раз",
          "R": 47,
          "U": 47,
          "mi": 0,
          "use": 1,
          "Rs": [0, 2],
          "Us": [],
          "im": "[cm]:coms"
        },
        {
          "description": "zzzzzz",
          "icon": "Attachment",
          "initVal": {},
          "title": "dwded",
          "R": 47,
          "U": 47,
          "mi": 1
        }
      ],
      "types": [
        {
          "tm": 60,
          "title": "Мал груп"
        }
      ],
      "tgInformTime": 5,
      "start": 1791666000000,
      "ctrl": {
        "cats": ["Основное"],
        "users": [
          {
            "fio": "Павел 👨‍💻",
            "login": "T166cbf17596a0c2919e4df1a6d54e66",
            "nick": "gfirf",
            "tgId": 958383738,
            "mi": 0,
            "R": 127
          },
          {
            "fio": "Джексон_С💙",
            "login": "T2844a791f6cb5702a875a0bad8e9397",
            "nick": "P_wife",
            "tgId": 1086988826,
            "mi": 1
          },
          {
            "fio": "User",
            "login": "8f9bfe9d1345237cb3b2b205864da075",
            "nick": "User",
            "mi": 2,
            "R": 47
          }
        ],
        "roles": [
          {
            "mi": 0,
            "title": "Координатор",
            "icon": "Teacher",
            "user": 0
          }
        ],
        "type": 5,
        "defu": 5
      },
      "games": {
        "criterias": [
          {
            "title": "Сила",
            "sorts": {}
          }
        ],
        "list": []
      },
      "lists": {
        "cats": [
          {
            "icon": "UserGroup",
            "title": "Группа",
            "titles": ["Наставники", "Участники"]
          }
        ],
        "units": [
          {
            "cat": 0,
            "mi": 1,
            "title": "Первая",
            "dsc": ""
          }
        ]
      },
      "w": 1726044545208.4993
    },
    {
      "title": "Сестринская конференция",
      "app": "index",
      "dsc": "Дорогие сестры, мы рады вас пригласить на молодёжную сестринскую  конференцию 💫\n\n📅 пятница 18 октября в 18:00 в малом зале \n\nМы будем говорить с вами об искушении девушек, затронем тему зависимости- от мнения людей, от соцсетей, от всего того, что уводит нас от Бога 🚫\n\nЖдём тебя 😇",
      "topic": "Искушения девушки",
      "days": [
        {
          "list": [
            {
              "type": 0,
              "mi": 0,
              "tgAlert": 1,
              "atts": {},
              "tgInform": 0,
              "tm": 30
            },
            {
              "type": 4,
              "mi": 4,
              "tgInform": 0
            },
            {
              "type": 1,
              "mi": 1,
              "tgAlert": 1,
              "atts": {
                "[cm]:coms": {
                  "comws": [1611851960664, 1611851960664, 1517518975000],
                  "eventw": 1611496603426
                }
              },
              "tgInform": 0,
              "tm": 5
            },
            {
              "type": 2,
              "mi": 2,
              "tgAlert": 1,
              "atts": {},
              "tgInform": 0,
              "dsc": "",
              "tm": 30,
              "topic": ""
            },
            {
              "type": 1,
              "mi": 5,
              "atts": {
                "[cm]:coms": {
                  "comws": [1517518975000],
                  "eventw": 1611496603426
                }
              },
              "tgInform": 0
            },
            {
              "type": 5,
              "mi": 6,
              "tgInform": 0
            },
            {
              "type": 1,
              "mi": 7,
              "atts": {
                "[cm]:coms": {
                  "eventw": 1611496603426
                }
              },
              "tgInform": 0
            },
            {
              "type": 6,
              "mi": 8,
              "tgInform": 0
            }
          ],
          "wup": 18,
          "mi": 0
        }
      ],
      "tatts": [
        {
          "description": "",
          "icon": "cast-outline",
          "initVal": {},
          "title": "Ход события",
          "R": 105,
          "U": 105,
          "mi": 0,
          "use": 113,
          "titles": ["лоывар", "ыволарыва"]
        }
      ],
      "types": [
        {
          "title": "Общение",
          "tm": 15
        },
        {
          "title": "Пение",
          "tm": 5,
          "atts": {}
        },
        {
          "title": "Проповедь",
          "tm": 90
        },
        {
          "title": "Разъезд",
          "tm": 5
        },
        {
          "tm": 5,
          "title": "Введение"
        },
        {
          "tm": 45,
          "title": "Свидетельства"
        },
        {
          "tm": 15,
          "title": "Молитва"
        }
      ],
      "tgInformTime": 5,
      "start": 1729198800000,
      "ctrl": {
        "cats": ["Основное"],
        "users": [
          {
            "fio": "danikpon",
            "login": "T7f21a14d3133065ca2e48254f87ecf3",
            "nick": "danikpon",
            "tgId": 370756745,
            "mi": 1,
            "tgInform": 1,
            "R": 127
          },
          {
            "fio": "Павел 👨‍💻",
            "login": "T166cbf17596a0c2919e4df1a6d54e66",
            "nick": "gfirf",
            "tgId": 958383738,
            "mi": 2,
            "R": 127
          }
        ],
        "roles": [
          {
            "mi": 0,
            "title": "Координатор",
            "icon": "github-outline"
          },
          {
            "title": "",
            "mi": 1
          }
        ],
        "type": 3,
        "defu": 21
      },
      "games": {
        "criterias": [
          {
            "title": "Сила",
            "sorts": {}
          }
        ],
        "list": []
      },
      "lists": {
        "cats": [
          {
            "icon": "people-outline",
            "title": "Группа",
            "titles": ["Наставники", "Участники"]
          }
        ],
        "units": [
          {
            "cat": 0,
            "mi": 1,
            "title": "Первая",
            "dsc": ""
          }
        ]
      },
      "w": 1728975804442.541,
      "tgAlertsTime": 30,
      "tgInform": 1
    }
  ]
}
